mappy_python-0.3.2.dist-info/METADATA
mappy_python-0.3.2.dist-info/WHEEL
mappy_python/__init__.py
mappy_python/mappy_python.cpython-313-x86_64-linux-gnu.so
mappy_python-0.3.2.dist-info/RECORD
